cloudforet/__init__.py
cloudforet/console_api_v2/__init__.py
cloudforet/console_api_v2/conf/__init__.py
cloudforet/console_api_v2/conf/global_conf.py
cloudforet/console_api_v2/conf/router_conf.py
cloudforet/console_api_v2/error/__init__.py
cloudforet/console_api_v2/error/cloudforet.py
cloudforet/console_api_v2/error/resource.py
cloudforet/console_api_v2/error/swagger.py
cloudforet/console_api_v2/interface/__init__.py
cloudforet/console_api_v2/interface/rest/__init__.py
cloudforet/console_api_v2/interface/rest/api.py
cloudforet/console_api_v2/interface/rest/proxy.py
cloudforet/console_api_v2/interface/rest/resource.py
cloudforet/console_api_v2/interface/rest/swagger.py
cloudforet/console_api_v2/manager/__init__.py
cloudforet/console_api_v2/manager/cloudforet_manager.py
cloudforet/console_api_v2/manager/resource_manager/__init__.py
cloudforet/console_api_v2/manager/resource_manager/cost_analysis_manager.py
cloudforet/console_api_v2/manager/resource_manager/inventory_manager.py
cloudforet/console_api_v2/model/__init__.py
cloudforet/console_api_v2/model/resource.py
cloudforet/console_api_v2/service/__init__.py
cloudforet/console_api_v2/service/proxy_service.py
cloudforet/console_api_v2/service/resource_service.py
cloudforet_console_api_v2-1.12.6.dist-info/METADATA
cloudforet_console_api_v2-1.12.6.dist-info/WHEEL
cloudforet_console_api_v2-1.12.6.dist-info/top_level.txt
cloudforet_console_api_v2-1.12.6.dist-info/RECORD
