Metadata-Version: 2.1
Name: cloudforet-console-api-v2
Version: 1.12.6
Summary: Cloudforet Console API v2 Service
Home-page: https://cloudforet.io/
Author: Cloudforet Admin
Author-email: admin@cloudforet.io
License: Apache License 2.0
Platform: UNKNOWN
